[
 {
  "description": "Pseudorandom test for KADD",
  "id": "kadd16",
  "format": "bin",
  "source": "kadd.asm",
  "option": "--bits 16 -w-ea-absolute -w-implicit-abs-deprecated -I./travis/insns/kadd/",
  "target": [
   { "output": "kadd.bin16", "match": "kadd.bin16.t" }
  ]
 }
,
 {
  "description": "Pseudorandom test for KADD",
  "id": "kadd32",
  "format": "bin",
  "source": "kadd.asm",
  "option": "--bits 32 -w-ea-absolute -w-implicit-abs-deprecated -I./travis/insns/kadd/",
  "target": [
   { "output": "kadd.bin32", "match": "kadd.bin32.t" }
  ]
 }
,
 {
  "description": "Pseudorandom test for KADD",
  "id": "kadd64",
  "format": "bin",
  "source": "kadd.asm",
  "option": "--bits 64 -w-ea-absolute -w-implicit-abs-deprecated -I./travis/insns/kadd/",
  "target": [
   { "output": "kadd.bin64", "match": "kadd.bin64.t" }
  ]
 }
]
