[
 {
  "description": "Pseudorandom test for ENCLV",
  "id": "enclv16",
  "format": "bin",
  "source": "enclv.asm",
  "option": "--bits 16 -w-ea-absolute -w-implicit-abs-deprecated -I./travis/insns/enclv/",
  "target": [
   { "output": "enclv.bin16", "match": "enclv.bin16.t" }
  ]
 }
,
 {
  "description": "Pseudorandom test for ENCLV",
  "id": "enclv32",
  "format": "bin",
  "source": "enclv.asm",
  "option": "--bits 32 -w-ea-absolute -w-implicit-abs-deprecated -I./travis/insns/enclv/",
  "target": [
   { "output": "enclv.bin32", "match": "enclv.bin32.t" }
  ]
 }
,
 {
  "description": "Pseudorandom test for ENCLV",
  "id": "enclv64",
  "format": "bin",
  "source": "enclv.asm",
  "option": "--bits 64 -w-ea-absolute -w-implicit-abs-deprecated -I./travis/insns/enclv/",
  "target": [
   { "output": "enclv.bin64", "match": "enclv.bin64.t" }
  ]
 }
]
