[
 {
  "description": "Pseudorandom test for ADDD",
  "id": "addd16",
  "format": "bin",
  "source": "addd.asm",
  "option": "--bits 16 -w-ea-absolute -w-implicit-abs-deprecated -I./travis/insns/addd/",
  "target": [
   { "output": "addd.bin16", "match": "addd.bin16.t" }
  ]
 }
,
 {
  "description": "Pseudorandom test for ADDD",
  "id": "addd32",
  "format": "bin",
  "source": "addd.asm",
  "option": "--bits 32 -w-ea-absolute -w-implicit-abs-deprecated -I./travis/insns/addd/",
  "target": [
   { "output": "addd.bin32", "match": "addd.bin32.t" }
  ]
 }
,
 {
  "description": "Pseudorandom test for ADDD",
  "id": "addd64",
  "format": "bin",
  "source": "addd.asm",
  "option": "--bits 64 -w-ea-absolute -w-implicit-abs-deprecated -I./travis/insns/addd/",
  "target": [
   { "output": "addd.bin64", "match": "addd.bin64.t" }
  ]
 }
]
