[
 {
  "description": "Pseudorandom test for CMPNEQSD",
  "id": "cmpneqsd16",
  "format": "bin",
  "source": "cmpneqsd_narrow.asm",
  "option": "--bits 16 -w-ea-absolute -w-implicit-abs-deprecated -I./travis/insns/cmpneqsd/",
  "target": [
   { "output": "cmpneqsd.bin16", "match": "cmpneqsd.bin16.t" }
  ]
 }
,
 {
  "description": "Pseudorandom test for CMPNEQSD",
  "id": "cmpneqsd32",
  "format": "bin",
  "source": "cmpneqsd_narrow.asm",
  "option": "--bits 32 -w-ea-absolute -w-implicit-abs-deprecated -I./travis/insns/cmpneqsd/",
  "target": [
   { "output": "cmpneqsd.bin32", "match": "cmpneqsd.bin32.t" }
  ]
 }
,
 {
  "description": "Pseudorandom test for CMPNEQSD",
  "id": "cmpneqsd64",
  "format": "bin",
  "source": "cmpneqsd.asm",
  "option": "--bits 64 -w-ea-absolute -w-implicit-abs-deprecated -I./travis/insns/cmpneqsd/",
  "target": [
   { "output": "cmpneqsd.bin64", "match": "cmpneqsd.bin64.t" }
  ]
 }
,
 {
  "description": "Pseudorandom error-case test for CMPNEQSD",
  "id": "cmpneqsd16err",
  "format": "bin",
  "source": "cmpneqsd_narrow.asm",
  "option": "--bits 16 -DERROR -w-ea-absolute -w-implicit-abs-deprecated -I./travis/insns/cmpneqsd/",
  "target": [
   { "stderr": "cmpneqsd.stderr16err" }
  ],
  "error": "expected"
 }
,
 {
  "description": "Pseudorandom error-case test for CMPNEQSD",
  "id": "cmpneqsd32err",
  "format": "bin",
  "source": "cmpneqsd_narrow.asm",
  "option": "--bits 32 -DERROR -w-ea-absolute -w-implicit-abs-deprecated -I./travis/insns/cmpneqsd/",
  "target": [
   { "stderr": "cmpneqsd.stderr32err" }
  ],
  "error": "expected"
 }
]
