[
 {
  "description": "Pseudorandom test for FMUL",
  "id": "fmul16",
  "format": "bin",
  "source": "fmul_narrow.asm",
  "option": "--bits 16 -w-ea-absolute -w-implicit-abs-deprecated -I./travis/insns/fmul/",
  "target": [
   { "output": "fmul.bin16", "match": "fmul.bin16.t" }
  ]
 }
,
 {
  "description": "Pseudorandom test for FMUL",
  "id": "fmul32",
  "format": "bin",
  "source": "fmul_narrow.asm",
  "option": "--bits 32 -w-ea-absolute -w-implicit-abs-deprecated -I./travis/insns/fmul/",
  "target": [
   { "output": "fmul.bin32", "match": "fmul.bin32.t" }
  ]
 }
,
 {
  "description": "Pseudorandom test for FMUL",
  "id": "fmul64",
  "format": "bin",
  "source": "fmul.asm",
  "option": "--bits 64 -w-ea-absolute -w-implicit-abs-deprecated -I./travis/insns/fmul/",
  "target": [
   { "output": "fmul.bin64", "match": "fmul.bin64.t" }
  ]
 }
]
