[
 {
  "description": "Pseudorandom test for INVPCID",
  "id": "invpcid16",
  "format": "bin",
  "source": "invpcid_narrow.asm",
  "option": "--bits 16 -w-ea-absolute -w-implicit-abs-deprecated -I./travis/insns/invpcid/",
  "target": [
   { "output": "invpcid.bin16", "match": "invpcid.bin16.t" }
  ]
 }
,
 {
  "description": "Pseudorandom test for INVPCID",
  "id": "invpcid32",
  "format": "bin",
  "source": "invpcid_narrow.asm",
  "option": "--bits 32 -w-ea-absolute -w-implicit-abs-deprecated -I./travis/insns/invpcid/",
  "target": [
   { "output": "invpcid.bin32", "match": "invpcid.bin32.t" }
  ]
 }
,
 {
  "description": "Pseudorandom error-case test for INVPCID",
  "id": "invpcid16err",
  "format": "bin",
  "source": "invpcid_narrow.asm",
  "option": "--bits 16 -DERROR -w-ea-absolute -w-implicit-abs-deprecated -I./travis/insns/invpcid/",
  "target": [
   { "stderr": "invpcid.stderr16err" }
  ],
  "error": "expected"
 }
,
 {
  "description": "Pseudorandom error-case test for INVPCID",
  "id": "invpcid32err",
  "format": "bin",
  "source": "invpcid_narrow.asm",
  "option": "--bits 32 -DERROR -w-ea-absolute -w-implicit-abs-deprecated -I./travis/insns/invpcid/",
  "target": [
   { "stderr": "invpcid.stderr32err" }
  ],
  "error": "expected"
 }
]
