[
 {
  "description": "Pseudorandom test for VCVTNEPS2BF16",
  "id": "vcvtneps2bf1616",
  "format": "bin",
  "source": "vcvtneps2bf16_narrow.asm",
  "option": "--bits 16 -w-ea-absolute -w-implicit-abs-deprecated -I./travis/insns/vcvtneps2bf16/",
  "target": [
   { "output": "vcvtneps2bf16.bin16", "match": "vcvtneps2bf16.bin16.t" }
  ]
 }
,
 {
  "description": "Pseudorandom test for VCVTNEPS2BF16",
  "id": "vcvtneps2bf1632",
  "format": "bin",
  "source": "vcvtneps2bf16_narrow.asm",
  "option": "--bits 32 -w-ea-absolute -w-implicit-abs-deprecated -I./travis/insns/vcvtneps2bf16/",
  "target": [
   { "output": "vcvtneps2bf16.bin32", "match": "vcvtneps2bf16.bin32.t" }
  ]
 }
,
 {
  "description": "Pseudorandom test for VCVTNEPS2BF16",
  "id": "vcvtneps2bf1664",
  "format": "bin",
  "source": "vcvtneps2bf16.asm",
  "option": "--bits 64 -w-ea-absolute -w-implicit-abs-deprecated -I./travis/insns/vcvtneps2bf16/",
  "target": [
   { "output": "vcvtneps2bf16.bin64", "match": "vcvtneps2bf16.bin64.t" }
  ]
 }
,
 {
  "description": "Pseudorandom error-case test for VCVTNEPS2BF16",
  "id": "vcvtneps2bf1616err",
  "format": "bin",
  "source": "vcvtneps2bf16_narrow.asm",
  "option": "--bits 16 -DERROR -w-ea-absolute -w-implicit-abs-deprecated -I./travis/insns/vcvtneps2bf16/",
  "target": [
   { "stderr": "vcvtneps2bf16.stderr16err" }
  ],
  "error": "expected"
 }
,
 {
  "description": "Pseudorandom error-case test for VCVTNEPS2BF16",
  "id": "vcvtneps2bf1632err",
  "format": "bin",
  "source": "vcvtneps2bf16_narrow.asm",
  "option": "--bits 32 -DERROR -w-ea-absolute -w-implicit-abs-deprecated -I./travis/insns/vcvtneps2bf16/",
  "target": [
   { "stderr": "vcvtneps2bf16.stderr32err" }
  ],
  "error": "expected"
 }
]
