[
 {
  "description": "Pseudorandom test for XORD",
  "id": "xord16",
  "format": "bin",
  "source": "xord.asm",
  "option": "--bits 16 -w-ea-absolute -w-implicit-abs-deprecated -I./travis/insns/xord/",
  "target": [
   { "output": "xord.bin16", "match": "xord.bin16.t" }
  ]
 }
,
 {
  "description": "Pseudorandom test for XORD",
  "id": "xord32",
  "format": "bin",
  "source": "xord.asm",
  "option": "--bits 32 -w-ea-absolute -w-implicit-abs-deprecated -I./travis/insns/xord/",
  "target": [
   { "output": "xord.bin32", "match": "xord.bin32.t" }
  ]
 }
,
 {
  "description": "Pseudorandom test for XORD",
  "id": "xord64",
  "format": "bin",
  "source": "xord.asm",
  "option": "--bits 64 -w-ea-absolute -w-implicit-abs-deprecated -I./travis/insns/xord/",
  "target": [
   { "output": "xord.bin64", "match": "xord.bin64.t" }
  ]
 }
]
