[
 {
  "description": "Pseudorandom test for VCVTTSH2SI",
  "id": "vcvttsh2si16",
  "format": "bin",
  "source": "vcvttsh2si_narrow.asm",
  "option": "--bits 16 -w-ea-absolute -w-implicit-abs-deprecated -I./travis/insns/vcvttsh2si/",
  "target": [
   { "output": "vcvttsh2si.bin16", "match": "vcvttsh2si.bin16.t" }
  ]
 }
,
 {
  "description": "Pseudorandom test for VCVTTSH2SI",
  "id": "vcvttsh2si32",
  "format": "bin",
  "source": "vcvttsh2si_narrow.asm",
  "option": "--bits 32 -w-ea-absolute -w-implicit-abs-deprecated -I./travis/insns/vcvttsh2si/",
  "target": [
   { "output": "vcvttsh2si.bin32", "match": "vcvttsh2si.bin32.t" }
  ]
 }
,
 {
  "description": "Pseudorandom test for VCVTTSH2SI",
  "id": "vcvttsh2si64",
  "format": "bin",
  "source": "vcvttsh2si.asm",
  "option": "--bits 64 -w-ea-absolute -w-implicit-abs-deprecated -I./travis/insns/vcvttsh2si/",
  "target": [
   { "output": "vcvttsh2si.bin64", "match": "vcvttsh2si.bin64.t" }
  ]
 }
,
 {
  "description": "Pseudorandom error-case test for VCVTTSH2SI",
  "id": "vcvttsh2si16err",
  "format": "bin",
  "source": "vcvttsh2si_narrow.asm",
  "option": "--bits 16 -DERROR -w-ea-absolute -w-implicit-abs-deprecated -I./travis/insns/vcvttsh2si/",
  "target": [
   { "stderr": "vcvttsh2si.stderr16err" }
  ],
  "error": "expected"
 }
,
 {
  "description": "Pseudorandom error-case test for VCVTTSH2SI",
  "id": "vcvttsh2si32err",
  "format": "bin",
  "source": "vcvttsh2si_narrow.asm",
  "option": "--bits 32 -DERROR -w-ea-absolute -w-implicit-abs-deprecated -I./travis/insns/vcvttsh2si/",
  "target": [
   { "stderr": "vcvttsh2si.stderr32err" }
  ],
  "error": "expected"
 }
]
