[
 {
  "description": "Pseudorandom test for KSHIFTRQ",
  "id": "kshiftrq16",
  "format": "bin",
  "source": "kshiftrq.asm",
  "option": "--bits 16 -w-ea-absolute -w-implicit-abs-deprecated -I./travis/insns/kshiftrq/",
  "target": [
   { "output": "kshiftrq.bin16", "match": "kshiftrq.bin16.t" }
  ]
 }
,
 {
  "description": "Pseudorandom test for KSHIFTRQ",
  "id": "kshiftrq32",
  "format": "bin",
  "source": "kshiftrq.asm",
  "option": "--bits 32 -w-ea-absolute -w-implicit-abs-deprecated -I./travis/insns/kshiftrq/",
  "target": [
   { "output": "kshiftrq.bin32", "match": "kshiftrq.bin32.t" }
  ]
 }
,
 {
  "description": "Pseudorandom test for KSHIFTRQ",
  "id": "kshiftrq64",
  "format": "bin",
  "source": "kshiftrq.asm",
  "option": "--bits 64 -w-ea-absolute -w-implicit-abs-deprecated -I./travis/insns/kshiftrq/",
  "target": [
   { "output": "kshiftrq.bin64", "match": "kshiftrq.bin64.t" }
  ]
 }
]
