[
 {
  "description": "Pseudorandom test for NOTQ",
  "id": "notq16",
  "format": "bin",
  "source": "notq.asm",
  "option": "--bits 16 -w-ea-absolute -w-implicit-abs-deprecated -I./travis/insns/notq/",
  "target": [
   { "output": "notq.bin16", "match": "notq.bin16.t" }
  ]
 }
,
 {
  "description": "Pseudorandom test for NOTQ",
  "id": "notq32",
  "format": "bin",
  "source": "notq.asm",
  "option": "--bits 32 -w-ea-absolute -w-implicit-abs-deprecated -I./travis/insns/notq/",
  "target": [
   { "output": "notq.bin32", "match": "notq.bin32.t" }
  ]
 }
,
 {
  "description": "Pseudorandom test for NOTQ",
  "id": "notq64",
  "format": "bin",
  "source": "notq.asm",
  "option": "--bits 64 -w-ea-absolute -w-implicit-abs-deprecated -I./travis/insns/notq/",
  "target": [
   { "output": "notq.bin64", "match": "notq.bin64.t" }
  ]
 }
]
